numsy/__init__.py
numsy/parser/__init__.py
numsy/parser/checker.py
numsy/parser/errors.py
numsy/parser/objects.py
numsy/parser/parser.py
numsy/parser/utility.py
numsy/solver/__init__.py
numsy/solver/core.py
numsy/solver/datatype.py
numsy/solver/errors.py
numsy/solver/logging.py
numsy/solver/matrices.py
numsy/solver/solve_algebra.py
numsy/solver/solve_basic.py
numsy/solver/utility.py
numsy-0.1.1.dist-info/LICENSE
numsy-0.1.1.dist-info/METADATA
numsy-0.1.1.dist-info/WHEEL
numsy-0.1.1.dist-info/top_level.txt
numsy-0.1.1.dist-info/RECORD
