Metadata-Version: 2.1
Name: numsy
Version: 0.1.1
Summary: Providing a powerful and accurate Math Solver.
Author-email: xCirno1 <xcirno6@gmail.com>
License: MIT License
Project-URL: Documentation, https://github.com/xCirno1/numsy
Project-URL: Issues, https://github.com/xCirno1/numsy/issues
Classifier: License :: OSI Approved :: MIT License
Classifier: Programming Language :: Python
Requires-Python: >=3.10
License-File: LICENSE
